sparx/__init__.py
sparx/data/prac1.txt
sparx/data/prac10.txt
sparx/data/prac2.txt
sparx/data/prac3.txt
sparx/data/prac4.txt
sparx/data/prac5.txt
sparx/data/prac6.txt
sparx/data/prac7.txt
sparx/data/prac8.txt
sparx/data/prac9.txt
sparx/data/requirements.txt
sparx_ai-1.1.0.dist-info/licenses/LICENSE
sparx_ai-1.1.0.dist-info/METADATA
sparx_ai-1.1.0.dist-info/WHEEL
sparx_ai-1.1.0.dist-info/top_level.txt
sparx_ai-1.1.0.dist-info/RECORD
